{
  "posts": [{
    "id": 1,
    "title": "json-server",
    "author": "typicode"
  }],
  "comments": [{
    "id": 1,
    "body": "some comment",
    "postId": 1
  }],
  "profile": {
    "name": "typicode"
  },
  "employeeData": [{
      "Enterprise_ID": "refika.koseler",
      "First_Name": "Refika",
      "Last_Name": "Koseler",
      "Supervisor_Name": "Rakesh Thomas",
      "Supervisor_EnterpriseId": "",
      "MyTE_Approver_Name": "Rakesh Thomas",
      "MyTE_Approver_ID": "",
      "User_ID": "rkoseler",
      "Contact_Number": "1 4808622167",
      "Career_Level": "C-Team Lead",
      "Cisco_Manager_Name": "Amy Papciak",
      "Portfolio_Name": "GSA",
      "Primary_Application": "GSA",
      "Location": "San Jose",
      "SOW_Number": ""
    },
    {
      "Enterprise_ID": "s.a.ranjan.sahoo",
      "First_Name": "Soumya Ranjan",
      "Last_Name": "Sahoo",
      "Supervisor_Name": "Arvind",
      "Supervisor_EnterpriseId": "arvind.walikar",
      "MyTE_Approver_Name": "Anupama",
      "MyTE_Approver_ID": "arvind.walikar",
      "User_ID": "soumyasa",
      "Contact_Number": "91 9739819018",
      "Career_Level": "10-Senior Software Engineer",
      "Cisco_Manager_Name": "Sylesh",
      "Portfolio_Name": "ES-Stock",
      "Primary_Application": "Stock",
      "Location": "Bangalore",
      "SOW_Number": ""
    },
    {
      "Enterprise_ID": "manuj.karanwal",
      "First_Name": "Karanwal",
      "Last_Name": "Manuj",
      "Supervisor_Name": "Srinivasa",
      "Supervisor_EnterpriseId": "",
      "MyTE_Approver_Name": "Gopi S",
      "MyTE_Approver_ID": "",
      "User_ID": "mkaranwa",
      "Contact_Number": "1 6099375285",
      "Career_Level": "C-Associate Manager",
      "Cisco_Manager_Name": "Uma Desiraju",
      "Portfolio_Name": "HRIT",
      "Primary_Application": "Insieme (Related to PTO) and Alto",
      "Location": "San Jose",
      "SOW_Number": ""
    },
    {
      "Enterprise_ID": "vijaykumar.ds",
      "First_Name": "Siva Vijaykumar",
      "Last_Name": "Doddi",
      "Supervisor_Name": "Srinivasa",
      "Supervisor_EnterpriseId": "",
      "MyTE_Approver_Name": "Srinivasa",
      "MyTE_Approver_ID": "",
      "User_ID": "vijds",
      "Contact_Number": "1 2167789831",
      "Career_Level": "08-Associate Manager",
      "Cisco_Manager_Name": "Uma Desiraju",
      "Portfolio_Name": "HRIT",
      "Primary_Application": "Payroll & Benefits",
      "Location": "San Jose",
      "SOW_Number": ""
    },
    {
      "Enterprise_ID": "a.sadashiv.dhapodkar",
      "First_Name": "Abhay Sadashiv",
      "Last_Name": "Dhapodkar",
      "Supervisor_Name": "Srinivasa",
      "Supervisor_EnterpriseId": "",
      "MyTE_Approver_Name": "Phani Bhushan",
      "MyTE_Approver_ID": "phani.bhushan.hari",
      "User_ID": "absadash",
      "Contact_Number": "91 88869-82000",
      "Career_Level": "09-Team Lead",
      "Cisco_Manager_Name": "Uma Desiraju",
      "Portfolio_Name": "HRIT",
      "Primary_Application": "HR IT-My Employee Information",
      "Location": "Hyderabad",
      "SOW_Number": ""
    },
    {
      "Enterprise_ID": "s.a.ranjan.sahoo",
      "First_Name": "Soumya Ranjan",
      "Last_Name": "Sahoo",
      "Supervisor_Name": "Arvind",
      "Supervisor_EnterpriseId": "arvind.walikar",
      "MyTE_Approver_Name": "Anupama",
      "MyTE_Approver_ID": "arvind.walikar",
      "User_ID": "soumyasa",
      "Contact_Number": "91 9739819018",
      "Career_Level": "10-Senior Software Engineer",
      "Cisco_Manager_Name": "Sylesh",
      "Portfolio_Name": "ES-Stock",
      "Primary_Application": "Stock",
      "Location": "Bangalore",
      "SOW_Number": ""
    },
    {
      "Enterprise_ID": "nagesh.sayibabu",
      "First_Name": "Nagesh",
      "Last_Name": "Sayibabu",
      "Supervisor_Name": "Raghavender",
      "Supervisor_EnterpriseId": "raghavender.jogaraju",
      "MyTE_Approver_Name": "Raghavender",
      "MyTE_Approver_ID": "raghavender.jogaraju",
      "User_ID": "nsayibab",
      "Contact_Number": "91 97400-76089",
      "Career_Level": "10-Senior Software Engineer",
      "Cisco_Manager_Name": "Sylesh",
      "Portfolio_Name": "ES-Mobility",
      "Primary_Application": "My Expense,Shark Tank",
      "Location": "Bangalore",
      "SOW_Number": "CSCOTQ00091810"
    },
    {
      "Enterprise_ID": "harshen.a.pandey",
      "First_Name": "Harshen Amarnath",
      "Last_Name": "Pandey",
      "Supervisor_Name": "Pratap Krishna",
      "Supervisor_EnterpriseId": "pratap.krishna.singh",
      "MyTE_Approver_Name": "Pratap Krishna",
      "MyTE_Approver_ID": "pratap.krishna.singh",
      "User_ID": "harpande",
      "Contact_Number": "91 9665666181",
      "Career_Level": "11-Software Engineer",
      "Cisco_Manager_Name": "Sylesh",
      "Portfolio_Name": "ES-Talent Market Place",
      "Primary_Application": "Talent Market Place",
      "Location": "Pune",
      "SOW_Number": "No updates"
    },
    {
      "Enterprise_ID": "anupama.omprakash",
      "First_Name": "Anupama",
      "Last_Name": "Om Prakash",
      "Supervisor_Name": "Niju Thomas",
      "Supervisor_EnterpriseId": "niju.thomas",
      "MyTE_Approver_Name": "Niju Thomas",
      "MyTE_Approver_ID": "niju.thomas",
      "User_ID": "aompraka",
      "Contact_Number": "91  98860-94803",
      "Career_Level": "08-Associate Manager",
      "Cisco_Manager_Name": "Chintan Desai",
      "Portfolio_Name": "iSecure/BATS/iLease",
      "Primary_Application": "Project Management",
      "Location": "Bangalore",
      "SOW_Number": "No updates"
    },
    {
      "Enterprise_ID": "l.veerappa",
      "First_Name": "Lokesh V",
      "Last_Name": "Veerappa",
      "Supervisor_Name": "Anupama",
      "Supervisor_EnterpriseId": "",
      "MyTE_Approver_Name": "Anupama",
      "MyTE_Approver_ID": "",
      "User_ID": "lveerapp",
      "Contact_Number": "91 99002-44075",
      "Career_Level": "09-Team Lead",
      "Cisco_Manager_Name": "Santosh Varagappa",
      "Portfolio_Name": "Oracle HRMS Automation",
      "Primary_Application": "Oracle HRMS",
      "Location": "Bangalore",
      "SOW_Number": "CSCOTQ00092732"
    },
    {
      "Enterprise_ID": "ramendra.kumar.jain",
      "First_Name": "Ramendra Kumar",
      "Last_Name": "Jain",
      "Supervisor_Name": "Jayaprakash Veerabasappa",
      "Supervisor_EnterpriseId": "jayaprakash.rokkada",
      "MyTE_Approver_Name": "Jayaprakash Veerabasappa",
      "MyTE_Approver_ID": "jayaprakash.rokkada",
      "User_ID": "ramjain",
      "Contact_Number": "91 8050005575",
      "Career_Level": "12-Associate Software Engineer",
      "Cisco_Manager_Name": "Chintan Desai",
      "Portfolio_Name": "Finance",
      "Primary_Application": "isecure",
      "Location": "Bangalore",
      "SOW_Number": "CSCOTQ00091436"
    },
    {
      "Enterprise_ID": "srinivasarao.ambati",
      "First_Name": "Srinivasarao",
      "Last_Name": "Amabati",
      "Supervisor_Name": "Arvind",
      "Supervisor_EnterpriseId": "arvind.walikar",
      "MyTE_Approver_Name": "Arvind",
      "MyTE_Approver_ID": "arvind.walikar",
      "User_ID": "samabati",
      "Contact_Number": "91 81520-50979",
      "Career_Level": "C-SSE",
      "Cisco_Manager_Name": "Sylesh",
      "Portfolio_Name": "ES-Stock",
      "Primary_Application": "Stock",
      "Location": "Bangalore",
      "SOW_Number": "CSCOTQ00092406"
    },
    {
      "Enterprise_ID": "ramya.kalaparthi",
      "First_Name": "Ramya",
      "Last_Name": "Kalaparthi",
      "Supervisor_Name": "Gopi Sammeta",
      "Supervisor_EnterpriseId": "gopi.s.sammeta",
      "MyTE_Approver_Name": "Gopi Sammeta",
      "MyTE_Approver_ID": "gopi.s.sammeta",
      "User_ID": "",
      "Contact_Number": "",
      "Career_Level": "09-Team Lead",
      "Cisco_Manager_Name": "F",
      "Portfolio_Name": "Feb-16",
      "Primary_Application": "Feb-16",
      "Location": "Goutam Reddy",
      "SOW_Number": "GL Lead"
    },
    {
      "Enterprise_ID": "sangeeta.naikar",
      "First_Name": "Sangeeta",
      "Last_Name": "Naikar",
      "Supervisor_Name": "Atul Gupt",
      "Supervisor_EnterpriseId": "atul.gupt",
      "MyTE_Approver_Name": "Atul Gupt",
      "MyTE_Approver_ID": "atul.gupt",
      "User_ID": "snaikar",
      "Contact_Number": "91 95381-45489",
      "Career_Level": "10-Senior Software Engineer",
      "Cisco_Manager_Name": "F",
      "Portfolio_Name": "Feb-15",
      "Primary_Application": "Mar-15",
      "Location": "Amy Papciak",
      "SOW_Number": "WPR-SSBR"
    },
    {
      "Enterprise_ID": "subbarao.maniam",
      "First_Name": "Subbarao",
      "Last_Name": "Maniam",
      "Supervisor_Name": "Phani Bhushan",
      "Supervisor_EnterpriseId": "phani.bhushan.hari",
      "MyTE_Approver_Name": "Phani Bhushan",
      "MyTE_Approver_ID": "phani.bhushan.hari",
      "User_ID": "smaniam",
      "Contact_Number": "91 99481-92444",
      "Career_Level": "10-Senior Software Engineer",
      "Cisco_Manager_Name": "M",
      "Portfolio_Name": "Feb-15",
      "Primary_Application": "Mar-15",
      "Location": "Amy Papciak",
      "SOW_Number": "WPR-SSBR"
    },
    {
      "Enterprise_ID": "srikar.pudi",
      "First_Name": "Srikar",
      "Last_Name": "Pudi",
      "Supervisor_Name": "Sheik Abdullah",
      "Supervisor_EnterpriseId": "sheik.abdullah.m",
      "MyTE_Approver_Name": "Sheik Abdullah",
      "MyTE_Approver_ID": "sheik.abdullah.m",
      "User_ID": "spudi",
      "Contact_Number": "91 9972179256",
      "Career_Level": "10-Senior Software Engineer",
      "Cisco_Manager_Name": "M",
      "Portfolio_Name": "Oct-15",
      "Primary_Application": "Oct-15",
      "Location": "Chintan Desai",
      "SOW_Number": "Finance"
    },
    {
      "Enterprise_ID": "govind.rajayogam",
      "First_Name": "Govind",
      "Last_Name": "Rajay",
      "Supervisor_Name": "Gopi Sammeta",
      "Supervisor_EnterpriseId": "gopi.s.sammeta",
      "MyTE_Approver_Name": "Gopi Sammeta",
      "MyTE_Approver_ID": "gopi.s.sammeta",
      "User_ID": "rgovind",
      "Contact_Number": "1 4085270817",
      "Career_Level": "C-Team Lead",
      "Cisco_Manager_Name": "M",
      "Portfolio_Name": "#N/A",
      "Primary_Application": "#N/A",
      "Location": "Romina Parikh",
      "SOW_Number": "Workforce Analytics & Reporting"
    },
    {
      "Enterprise_ID": "r.kumar.agrahari",
      "First_Name": "Ritesh Kumar Agrahari",
      "Last_Name": "Ritesh Kumar",
      "Supervisor_Name": "Agrahari",
      "Supervisor_EnterpriseId": "Phani Bhushan",
      "MyTE_Approver_Name": "phani.bhushan.hari",
      "MyTE_Approver_ID": "Phani Bhushan",
      "User_ID": "phani.bhushan.hari",
      "Contact_Number": "Phani Bhushan",
      "Career_Level": "phani.bhushan.hari",
      "Cisco_Manager_Name": "Phani Bhushan",
      "Portfolio_Name": "phani.bhushan.hari",
      "Primary_Application": "rkumarag",
      "Location": "91 97412-94343",
      "SOW_Number": "11-Software Engineer"
    },
    {
      "Enterprise_ID": "bhaskar.vangimalla",
      "First_Name": "Bhaskar Vangimalla",
      "Last_Name": "Bhaskar",
      "Supervisor_Name": "Vangimalla",
      "Supervisor_EnterpriseId": "Lokesh Thadani",
      "MyTE_Approver_Name": "lokesh.thadani",
      "MyTE_Approver_ID": "Lokesh Thadani",
      "User_ID": "lokesh.thadani",
      "Contact_Number": "Lokesh Thadani",
      "Career_Level": "lokesh.thadani",
      "Cisco_Manager_Name": "Phani Bhushan",
      "Portfolio_Name": "phani.bhushan.hari",
      "Primary_Application": "bvangima",
      "Location": "91 8097864784",
      "SOW_Number": "10-Senior Software Engineer"
    },
    {
      "Enterprise_ID": "veda.penugonda",
      "First_Name": "Veda Lakshmi Penugonda",
      "Last_Name": "VedaLakshmi",
      "Supervisor_Name": "Penugonda",
      "Supervisor_EnterpriseId": "Abdul Quddus",
      "MyTE_Approver_Name": "a.quddus",
      "MyTE_Approver_ID": "Abdul Quddus",
      "User_ID": "a.quddus",
      "Contact_Number": "Abdul Quddus",
      "Career_Level": "a.quddus",
      "Cisco_Manager_Name": "Phani Bhushan",
      "Portfolio_Name": "phani.bhushan.hari",
      "Primary_Application": "",
      "Location": "",
      "SOW_Number": "11-Software Engineer"
    },
    {
      "Enterprise_ID": "jayanti.kumari",
      "First_Name": "Jayanti Kumari",
      "Last_Name": "Jayanti",
      "Supervisor_Name": "Kumari",
      "Supervisor_EnterpriseId": "Manjunath Bariki",
      "MyTE_Approver_Name": "manjunath.bariki",
      "MyTE_Approver_ID": "Manjunath Bariki",
      "User_ID": "manjunath.bariki",
      "Contact_Number": "Manjunath Bariki",
      "Career_Level": "manjunath.bariki",
      "Cisco_Manager_Name": "Niju Thomas",
      "Portfolio_Name": "niju.thomas",
      "Primary_Application": "jakumari",
      "Location": "91 81050-99877",
      "SOW_Number": "10-Senior Software Engineer"
    },
    {
      "Enterprise_ID": "chinu.subudhi",
      "First_Name": "Chinu Subudhi",
      "Last_Name": "Chinu",
      "Supervisor_Name": "Subudhi",
      "Supervisor_EnterpriseId": "Raghavender",
      "MyTE_Approver_Name": "raghavender.jogaraju",
      "MyTE_Approver_ID": "Raghavender",
      "User_ID": "raghavender.jogaraju",
      "Contact_Number": "Raghavender",
      "Career_Level": "raghavender.jogaraju",
      "Cisco_Manager_Name": "Raghavender",
      "Portfolio_Name": "raghavender.jogaraju",
      "Primary_Application": "chisubud",
      "Location": "91 99018-82194",
      "SOW_Number": "09-Team Lead"
    },
    {
      "Enterprise_ID": "jayaprakash.rokkada",
      "First_Name": "Jayaprakash Veerabasappa Rokkada",
      "Last_Name": "Jayaprakash Veerabasappa",
      "Supervisor_Name": "Rokkada",
      "Supervisor_EnterpriseId": "Niju Thomas",
      "MyTE_Approver_Name": "niju.thomas",
      "MyTE_Approver_ID": "Niju Thomas",
      "User_ID": "niju.thomas",
      "Contact_Number": "Niju Thomas",
      "Career_Level": "niju.thomas",
      "Cisco_Manager_Name": "Niju Thomas",
      "Portfolio_Name": "niju.thomas",
      "Primary_Application": "jrokkada",
      "Location": "91  9740516256",
      "SOW_Number": "08-Associate Manager"
    },
    {
      "Enterprise_ID": "atul.gupt",
      "First_Name": "Atul Gupta",
      "Last_Name": "Atul",
      "Supervisor_Name": "Gupt",
      "Supervisor_EnterpriseId": "Rakesh Thomas",
      "MyTE_Approver_Name": "rakesh.thomas",
      "MyTE_Approver_ID": "Phani Bhushan",
      "User_ID": "phani.bhushan.hari",
      "Contact_Number": "Phani Bhushan",
      "Career_Level": "phani.bhushan.hari",
      "Cisco_Manager_Name": "Phani Bhushan",
      "Portfolio_Name": "phani.bhushan.hari",
      "Primary_Application": "atulg2",
      "Location": "91 98869-88859",
      "SOW_Number": "09-Team Lead"
    },
    {
      "Enterprise_ID": "gurpreet.e.kaur",
      "First_Name": "Gurpreet Kaur",
      "Last_Name": "Gurpreet",
      "Supervisor_Name": "Kaur",
      "Supervisor_EnterpriseId": "Raghavender",
      "MyTE_Approver_Name": "raghavender.jogaraju",
      "MyTE_Approver_ID": "Raghavender",
      "User_ID": "raghavender.jogaraju",
      "Contact_Number": "Raghavender",
      "Career_Level": "raghavender.jogaraju",
      "Cisco_Manager_Name": "Raghavender",
      "Portfolio_Name": "raghavender.jogaraju",
      "Primary_Application": "gurpkau2",
      "Location": "91 98455-33536",
      "SOW_Number": "09-Team Lead"
    },
    {
      "Enterprise_ID": "jyoti.a.tiwari",
      "First_Name": "Jyoti Tiwari",
      "Last_Name": "Jyoti",
      "Supervisor_Name": "Tiwari",
      "Supervisor_EnterpriseId": "Manjunath Bariki",
      "MyTE_Approver_Name": "manjunath.bariki",
      "MyTE_Approver_ID": "Manjunath Bariki",
      "User_ID": "manjunath.bariki",
      "Contact_Number": "Manjunath Bariki",
      "Career_Level": "manjunath.bariki",
      "Cisco_Manager_Name": "Niju Thomas",
      "Portfolio_Name": "niju.thomas",
      "Primary_Application": "jtiwari",
      "Location": "91 8088401883",
      "SOW_Number": "11-Software Engineer"
    },
    {
      "Enterprise_ID": "t.selvan",
      "First_Name": "Tamil Selvan Subbaiah",
      "Last_Name": "Tamil Selvan",
      "Supervisor_Name": "Subbaiah",
      "Supervisor_EnterpriseId": "Niju Thomas",
      "MyTE_Approver_Name": "niju.thomas",
      "MyTE_Approver_ID": "Niju Thomas",
      "User_ID": "niju.thomas",
      "Contact_Number": "Niju Thomas",
      "Career_Level": "niju.thomas",
      "Cisco_Manager_Name": "Niju Thomas",
      "Portfolio_Name": "niju.thomas",
      "Primary_Application": "tsubbaia",
      "Location": "91 98 8664 7842",
      "SOW_Number": "08-Associate Manager"
    },
    {
      "Enterprise_ID": "d.novelo.carrillo",
      "First_Name": "David Carrilo",
      "Last_Name": "David",
      "Supervisor_Name": "Carrillo",
      "Supervisor_EnterpriseId": "Gopi Sammeta",
      "MyTE_Approver_Name": "gopi.s.sammeta",
      "MyTE_Approver_ID": "Gopi Sammeta",
      "User_ID": "gopi.s.sammeta",
      "Contact_Number": "",
      "Career_Level": "",
      "Cisco_Manager_Name": "",
      "Portfolio_Name": "",
      "Primary_Application": "",
      "Location": "",
      "SOW_Number": "10-Senior Software Engineer"
    },
    {
      "Enterprise_ID": "satish.sirigirisetty",
      "First_Name": "Satish Sirigirisetty",
      "Last_Name": "Satish",
      "Supervisor_Name": "Sirigirisetty",
      "Supervisor_EnterpriseId": "Pramod Gupta",
      "MyTE_Approver_Name": "pramod.x.gupta",
      "MyTE_Approver_ID": "Gopi Sammeta",
      "User_ID": "gopi.s.sammeta",
      "Contact_Number": "",
      "Career_Level": "",
      "Cisco_Manager_Name": "",
      "Portfolio_Name": "",
      "Primary_Application": "sasirigi",
      "Location": "1 4085270817",
      "SOW_Number": "C-Team Lead"
    },
    {
      "Enterprise_ID": "s.gumma",
      "First_Name": "Srikrishna Gumma",
      "Last_Name": "Srikrishna",
      "Supervisor_Name": "Gumma",
      "Supervisor_EnterpriseId": "Kiran  Avaral",
      "MyTE_Approver_Name": "kiran.avaral",
      "MyTE_Approver_ID": "Kiran  Avaral",
      "User_ID": "kiran.avaral",
      "Contact_Number": "",
      "Career_Level": "",
      "Cisco_Manager_Name": "",
      "Portfolio_Name": "",
      "Primary_Application": "sgumma",
      "Location": "1 4088136697",
      "SOW_Number": "08-Associate Manager"
    },
    {
      "Enterprise_ID": "rakesh.thomas",
      "First_Name": "Rakesh Thomas",
      "Last_Name": "Rakesh Thomas",
      "Supervisor_Name": "Kizhakkekara",
      "Supervisor_EnterpriseId": "Kiran  Avaral",
      "MyTE_Approver_Name": "kiran.avaral",
      "MyTE_Approver_ID": "Kiran  Avaral",
      "User_ID": "kiran.avaral",
      "Contact_Number": "",
      "Career_Level": "",
      "Cisco_Manager_Name": "",
      "Portfolio_Name": "",
      "Primary_Application": "rkizhakk",
      "Location": "1 6124029954",
      "SOW_Number": "08-Associate Manager"
    },
    {
      "Enterprise_ID": "mayank.d.srivastava",
      "First_Name": "Mayank Srivastava",
      "Last_Name": "Mayank",
      "Supervisor_Name": "Srivastava",
      "Supervisor_EnterpriseId": "Manjunath Bariki",
      "MyTE_Approver_Name": "manjunath.bariki",
      "MyTE_Approver_ID": "Manjunath Bariki",
      "User_ID": "manjunath.bariki",
      "Contact_Number": "Manjunath Bariki",
      "Career_Level": "manjunath.bariki",
      "Cisco_Manager_Name": "Niju Thomas",
      "Portfolio_Name": "niju.thomas",
      "Primary_Application": "mayansri",
      "Location": "91 9790767939",
      "SOW_Number": "10-Senior Software Engineer"
    },
    {
      "Enterprise_ID": "a.a.dixit",
      "First_Name": "Abhishek Dixit",
      "Last_Name": "Abhishek",
      "Supervisor_Name": "Dixit",
      "Supervisor_EnterpriseId": "Abdul Quddus",
      "MyTE_Approver_Name": "a.quddus",
      "MyTE_Approver_ID": "Abdul Quddus",
      "User_ID": "a.quddus",
      "Contact_Number": "Abdul Quddus",
      "Career_Level": "a.quddus",
      "Cisco_Manager_Name": "Harish Br",
      "Portfolio_Name": "harish.br",
      "Primary_Application": "abdixit",
      "Location": "91 9739776533",
      "SOW_Number": "11-Software Engineer"
    },
    {
      "Enterprise_ID": "sudeep.goyal",
      "First_Name": "Sudeep Goyal",
      "Last_Name": "Sudeep",
      "Supervisor_Name": "Goyal",
      "Supervisor_EnterpriseId": "Niju Thomas",
      "MyTE_Approver_Name": "niju.thomas",
      "MyTE_Approver_ID": "Niju Thomas",
      "User_ID": "niju.thomas",
      "Contact_Number": "Niju Thomas",
      "Career_Level": "niju.thomas",
      "Cisco_Manager_Name": "Niju Thomas",
      "Portfolio_Name": "niju.thomas",
      "Primary_Application": "sugoyal",
      "Location": "",
      "SOW_Number": "08-Associate Manager"
    },
    {
      "Enterprise_ID": "suneeth.chadalawada",
      "First_Name": "Suneeth Chadalawada",
      "Last_Name": "Suneeth",
      "Supervisor_Name": "Chadalawada",
      "Supervisor_EnterpriseId": "Gopi Sammeta",
      "MyTE_Approver_Name": "gopi.s.sammeta",
      "MyTE_Approver_ID": "Gopi Sammeta",
      "User_ID": "gopi.s.sammeta",
      "Contact_Number": "",
      "Career_Level": "",
      "Cisco_Manager_Name": "",
      "Portfolio_Name": "",
      "Primary_Application": "suchadal",
      "Location": "1 2016006147",
      "SOW_Number": "C-Associate Manager"
    },
    {
      "Enterprise_ID": "praful.kumar.nath",
      "First_Name": "Praful Kumar Nath",
      "Last_Name": "Praful",
      "Supervisor_Name": "Kumarnath",
      "Supervisor_EnterpriseId": "Lokesh Thadani",
      "MyTE_Approver_Name": "lokesh.thadani",
      "MyTE_Approver_ID": "Lokesh Thadani",
      "User_ID": "lokesh.thadani",
      "Contact_Number": "Lokesh Thadani",
      "Career_Level": "lokesh.thadani",
      "Cisco_Manager_Name": "Harish Br",
      "Portfolio_Name": "harish.br",
      "Primary_Application": "",
      "Location": "",
      "SOW_Number": "C-SSE"
    },
    {
      "Enterprise_ID": "prathap.kumar.gowda",
      "First_Name": "Pratap Krishna Singh",
      "Last_Name": "Pratap Krishna",
      "Supervisor_Name": "Singh",
      "Supervisor_EnterpriseId": "",
      "MyTE_Approver_Name": "",
      "MyTE_Approver_ID": "",
      "User_ID": "",
      "Contact_Number": "Girisha.adaveeshiah",
      "Career_Level": "Girisha.adaveeshiah",
      "Cisco_Manager_Name": "Girisha.adaveeshiah",
      "Portfolio_Name": "Girisha.adaveeshiah",
      "Primary_Application": "",
      "Location": "",
      "SOW_Number": "10-Senior Software Engineer"
    },
    {
      "Enterprise_ID": "pallabi.panigrahi",
      "First_Name": "Pallabi Panigrahi",
      "Last_Name": "Pallabi Panigrahi",
      "Supervisor_Name": "Singh",
      "Supervisor_EnterpriseId": "Atul Gupt",
      "MyTE_Approver_Name": "atul.gupt",
      "MyTE_Approver_ID": "Atul Gupt",
      "User_ID": "atul.gupt",
      "Contact_Number": "Atul Gupt",
      "Career_Level": "atul.gupt",
      "Cisco_Manager_Name": "Phani Bhushan",
      "Portfolio_Name": "phani.bhushan.hari",
      "Primary_Application": "ppanigra",
      "Location": "91 98866-60524",
      "SOW_Number": "11-Software Engineer"
    },
    {
      "Enterprise_ID": "chetan.b.gupta",
      "First_Name": "Chetan Gupta",
      "Last_Name": "Chetan",
      "Supervisor_Name": "Gupta",
      "Supervisor_EnterpriseId": "Phani Bhushan",
      "MyTE_Approver_Name": "phani.bhushan.hari",
      "MyTE_Approver_ID": "Phani Bhushan",
      "User_ID": "phani.bhushan.hari",
      "Contact_Number": "Phani Bhushan",
      "Career_Level": "phani.bhushan.hari",
      "Cisco_Manager_Name": "Phani Bhushan",
      "Portfolio_Name": "phani.bhushan.hari",
      "Primary_Application": "",
      "Location": "",
      "SOW_Number": "11-Software Engineer"
    },
    {
      "Enterprise_ID": "abhis.gupta",
      "First_Name": "Abhishek Gupta",
      "Last_Name": "Abhishek",
      "Supervisor_Name": "Gupta",
      "Supervisor_EnterpriseId": "Tirumala",
      "MyTE_Approver_Name": "tirumala.betamcharla",
      "MyTE_Approver_ID": "Tirumala",
      "User_ID": "tirumala.betamcharla",
      "Contact_Number": "Tirumala",
      "Career_Level": "tirumala.betamcharla",
      "Cisco_Manager_Name": "Raghavender",
      "Portfolio_Name": "raghavender.jogaraju",
      "Primary_Application": "abgupta4",
      "Location": "91 98966-59894",
      "SOW_Number": "10-Senior Software Engineer"
    },
    {
      "Enterprise_ID": "m.kempaiah",
      "First_Name": "#REF!",
      "Last_Name": "Mahadevaswamy",
      "Supervisor_Name": "Kempaiah",
      "Supervisor_EnterpriseId": "Annada Prasanna",
      "MyTE_Approver_Name": "a.prasanna.sahoo",
      "MyTE_Approver_ID": "Annada Prasanna",
      "User_ID": "a.prasanna.sahoo",
      "Contact_Number": "Annada Prasanna",
      "Career_Level": "a.prasanna.sahoo",
      "Cisco_Manager_Name": "Raghavender",
      "Portfolio_Name": "raghavender.jogaraju",
      "Primary_Application": "mahkempa",
      "Location": "91 90089-48014",
      "SOW_Number": "10-Senior Software Engineer"
    },
    {
      "Enterprise_ID": "anuradha.basavaraju",
      "First_Name": "Anuradha Basavaraju",
      "Last_Name": "Anuradha",
      "Supervisor_Name": "Basavaraju",
      "Supervisor_EnterpriseId": "Harish Br",
      "MyTE_Approver_Name": "harish.br",
      "MyTE_Approver_ID": "Harish Br",
      "User_ID": "harish.br",
      "Contact_Number": "Harish Br",
      "Career_Level": "harish.br",
      "Cisco_Manager_Name": "Harish Br",
      "Portfolio_Name": "harish.br",
      "Primary_Application": "anub",
      "Location": "91 9986215431",
      "SOW_Number": "09-Team Lead"
    },
    {
      "Enterprise_ID": "v.venkatarathnam",
      "First_Name": "Vinitha Venkatarathnam",
      "Last_Name": "Vinitha",
      "Supervisor_Name": "Venkatarathnam",
      "Supervisor_EnterpriseId": "Phani Bhushan",
      "MyTE_Approver_Name": "phani.bhushan.hari",
      "MyTE_Approver_ID": "Phani Bhushan",
      "User_ID": "phani.bhushan.hari",
      "Contact_Number": "Phani Bhushan",
      "Career_Level": "phani.bhushan.hari",
      "Cisco_Manager_Name": "Phani Bhushan",
      "Portfolio_Name": "phani.bhushan.hari",
      "Primary_Application": "",
      "Location": "",
      "SOW_Number": "12-Associate Software Engineer"
    },
    {
      "Enterprise_ID": "n.nayak",
      "First_Name": "Neha Nayak",
      "Last_Name": "Neha",
      "Supervisor_Name": "Nayak",
      "Supervisor_EnterpriseId": "Phani Bhushan",
      "MyTE_Approver_Name": "phani.bhushan.hari",
      "MyTE_Approver_ID": "Phani Bhushan",
      "User_ID": "phani.bhushan.hari",
      "Contact_Number": "Phani Bhushan",
      "Career_Level": "phani.bhushan.hari",
      "Cisco_Manager_Name": "Phani Bhushan",
      "Portfolio_Name": "phani.bhushan.hari",
      "Primary_Application": "",
      "Location": "",
      "SOW_Number": "12-Associate Software Engineer"
    },
    {
      "Enterprise_ID": "",
      "First_Name": "siva.nekkalapudi",
      "Last_Name": "Siva Nekkalapudi",
      "Supervisor_Name": "Siva",
      "Supervisor_EnterpriseId": "Nekkalapudi",
      "MyTE_Approver_Name": "Srinivasa Sunchu",
      "MyTE_Approver_ID": "srinivasa.sunchu",
      "User_ID": "Srinivasa Sunchu",
      "Contact_Number": "srinivasa.sunchu",
      "Career_Level": "",
      "Cisco_Manager_Name": "",
      "Portfolio_Name": "",
      "Primary_Application": "",
      "Location": "snekkala",
      "SOW_Number": 8326556789,
      "": "No"
    },
    {
      "Enterprise_ID": "ashok.renukaradhya",
      "First_Name": "Ashok Panditanahalli",
      "Last_Name": "Renukaradhya",
      "Supervisor_Name": "Tirumala",
      "Supervisor_EnterpriseId": "tirumala.betamcharla",
      "MyTE_Approver_Name": "Tirumala",
      "MyTE_Approver_ID": "tirumala.betamcharla",
      "User_ID": "arenukar",
      "Contact_Number": "91 9731887942",
      "Career_Level": "10-Senior Software Engineer",
      "Cisco_Manager_Name": "Sangeetha R",
      "Portfolio_Name": "P2R-My Expense",
      "Primary_Application": "My Expense",
      "Location": "Bangalore",
      "SOW_Number": "CSCOTQ00091810"
    },
    {
      "Enterprise_ID": "anvesh.singamsetty",
      "First_Name": "Anvesh Singamsetty",
      "Last_Name": "Anvesh",
      "Supervisor_Name": "Singamsetty",
      "Supervisor_EnterpriseId": "phani.bhushan.hari",
      "MyTE_Approver_Name": "Phani Bhushan",
      "MyTE_Approver_ID": "phani.bhushan.hari",
      "User_ID": "asingams",
      "Contact_Number": "+91 81231-46869",
      "Career_Level": "11-Software Engineer",
      "Cisco_Manager_Name": "Amy Papciak",
      "Portfolio_Name": "WPR-SSBR",
      "Primary_Application": "WPR Allocations",
      "Location": "Bangalore",
      "SOW_Number": "CSCOTQ00092136"
    }
  ]
}
