{
  "posts": [{
    "id": 1,
    "title": "json-server",
    "author": "typicode"
  }],
  "comments": [{
    "id": 1,
    "body": "some comment",
    "postId": 1
  }],
  "profile": {
    "name": "typicode"
  },
  "employeeData": [{
      "Enterprise ID": "refika.koseler",
      "FirstName": "Refika",
      "LastName": "Koseler",
      "Supervisor": "Rakesh Thomas",
      "EnterpriseId-Supervisor": "",
      "MyTE Approver": "Rakesh Thomas",
      "EnterpriseId-myteapprover": "",
      "Userid": "rkoseler",
      "Contact No": "1 4808622167",
      "Career Level": "C-Team Lead",
      "Cisco Manager": "Amy Papciak",
      "Portfolio name": "GSA",
      "Primary Application": "GSA",
      "Location": "San Jose",
      "SOW#": ""
    },
    {
      "Enterprise ID": "s.a.ranjan.sahoo",
      "FirstName": "Soumya Ranjan",
      "LastName": "Sahoo",
      "Supervisor": "Arvind",
      "EnterpriseId-Supervisor": "arvind.walikar",
      "MyTE Approver": "Anupama",
      "EnterpriseId-myteapprover": "arvind.walikar",
      "Userid": "soumyasa",
      "Contact No": "91 9739819018",
      "Career Level": "10-Senior Software Engineer",
      "Cisco Manager": "Sylesh",
      "Portfolio name": "ES-Stock",
      "Primary Application": "Stock",
      "Location": "Bangalore",
      "SOW#": ""
    },
    {
      "Enterprise ID": "manuj.karanwal",
      "FirstName": "Karanwal",
      "LastName": "Manuj",
      "Supervisor": "Srinivasa",
      "EnterpriseId-Supervisor": "",
      "MyTE Approver": "Gopi S",
      "EnterpriseId-myteapprover": "",
      "Userid": "mkaranwa",
      "Contact No": "1 6099375285",
      "Career Level": "C-Associate Manager",
      "Cisco Manager": "Uma Desiraju",
      "Portfolio name": "HRIT",
      "Primary Application": "Insieme (Related to PTO) and Alto",
      "Location": "San Jose",
      "SOW#": ""
    },
    {
      "Enterprise ID": "vijaykumar.ds",
      "FirstName": "Siva Vijaykumar",
      "LastName": "Doddi",
      "Supervisor": "Srinivasa",
      "EnterpriseId-Supervisor": "",
      "MyTE Approver": "Srinivasa",
      "EnterpriseId-myteapprover": "",
      "Userid": "vijds",
      "Contact No": "1 2167789831",
      "Career Level": "08-Associate Manager",
      "Cisco Manager": "Uma Desiraju",
      "Portfolio name": "HRIT",
      "Primary Application": "Payroll & Benefits",
      "Location": "San Jose",
      "SOW#": ""
    },
    {
      "Enterprise ID": "a.sadashiv.dhapodkar",
      "FirstName": "Abhay Sadashiv",
      "LastName": "Dhapodkar",
      "Supervisor": "Srinivasa",
      "EnterpriseId-Supervisor": "",
      "MyTE Approver": "Phani Bhushan",
      "EnterpriseId-myteapprover": "phani.bhushan.hari",
      "Userid": "absadash",
      "Contact No": "91 88869-82000",
      "Career Level": "09-Team Lead",
      "Cisco Manager": "Uma Desiraju",
      "Portfolio name": "HRIT",
      "Primary Application": "HR IT-My Employee Information",
      "Location": "Hyderabad",
      "SOW#": ""
    },
    {
      "Enterprise ID": "s.a.ranjan.sahoo",
      "FirstName": "Soumya Ranjan",
      "LastName": "Sahoo",
      "Supervisor": "Arvind",
      "EnterpriseId-Supervisor": "arvind.walikar",
      "MyTE Approver": "Anupama",
      "EnterpriseId-myteapprover": "arvind.walikar",
      "Userid": "soumyasa",
      "Contact No": "91 9739819018",
      "Career Level": "10-Senior Software Engineer",
      "Cisco Manager": "Sylesh",
      "Portfolio name": "ES-Stock",
      "Primary Application": "Stock",
      "Location": "Bangalore",
      "SOW#": ""
    },
    {
      "Enterprise ID": "nagesh.sayibabu",
      "FirstName": "Nagesh",
      "LastName": "Sayibabu",
      "Supervisor": "Raghavender",
      "EnterpriseId-Supervisor": "raghavender.jogaraju",
      "MyTE Approver": "Raghavender",
      "EnterpriseId-myteapprover": "raghavender.jogaraju",
      "Userid": "nsayibab",
      "Contact No": "91 97400-76089",
      "Career Level": "10-Senior Software Engineer",
      "Cisco Manager": "Sylesh",
      "Portfolio name": "ES-Mobility",
      "Primary Application": "My Expense,Shark Tank",
      "Location": "Bangalore",
      "SOW#": "CSCOTQ00091810"
    },
    {
      "Enterprise ID": "harshen.a.pandey",
      "FirstName": "Harshen Amarnath",
      "LastName": "Pandey",
      "Supervisor": "Pratap Krishna",
      "EnterpriseId-Supervisor": "pratap.krishna.singh",
      "MyTE Approver": "Pratap Krishna",
      "EnterpriseId-myteapprover": "pratap.krishna.singh",
      "Userid": "harpande",
      "Contact No": "91 9665666181",
      "Career Level": "11-Software Engineer",
      "Cisco Manager": "Sylesh",
      "Portfolio name": "ES-Talent Market Place",
      "Primary Application": "Talent Market Place",
      "Location": "Pune",
      "SOW#": "No updates"
    },
    {
      "Enterprise ID": "anupama.omprakash",
      "FirstName": "Anupama",
      "LastName": "Om Prakash",
      "Supervisor": "Niju Thomas",
      "EnterpriseId-Supervisor": "niju.thomas",
      "MyTE Approver": "Niju Thomas",
      "EnterpriseId-myteapprover": "niju.thomas",
      "Userid": "aompraka",
      "Contact No": "91  98860-94803",
      "Career Level": "08-Associate Manager",
      "Cisco Manager": "Chintan Desai",
      "Portfolio name": "iSecure/BATS/iLease",
      "Primary Application": "Project Management",
      "Location": "Bangalore",
      "SOW#": "No updates"
    },
    {
      "Enterprise ID": "l.veerappa",
      "FirstName": "Lokesh V",
      "LastName": "Veerappa",
      "Supervisor": "Anupama",
      "EnterpriseId-Supervisor": "",
      "MyTE Approver": "Anupama",
      "EnterpriseId-myteapprover": "",
      "Userid": "lveerapp",
      "Contact No": "91 99002-44075",
      "Career Level": "09-Team Lead",
      "Cisco Manager": "Santosh Varagappa",
      "Portfolio name": "Oracle HRMS Automation",
      "Primary Application": "Oracle HRMS",
      "Location": "Bangalore",
      "SOW#": "CSCOTQ00092732"
    },
    {
      "Enterprise ID": "ramendra.kumar.jain",
      "FirstName": "Ramendra Kumar",
      "LastName": "Jain",
      "Supervisor": "Jayaprakash Veerabasappa",
      "EnterpriseId-Supervisor": "jayaprakash.rokkada",
      "MyTE Approver": "Jayaprakash Veerabasappa",
      "EnterpriseId-myteapprover": "jayaprakash.rokkada",
      "Userid": "ramjain",
      "Contact No": "91 8050005575",
      "Career Level": "12-Associate Software Engineer",
      "Cisco Manager": "Chintan Desai",
      "Portfolio name": "Finance",
      "Primary Application": "isecure",
      "Location": "Bangalore",
      "SOW#": "CSCOTQ00091436"
    },
    {
      "Enterprise ID": "srinivasarao.ambati",
      "FirstName": "Srinivasarao",
      "LastName": "Amabati",
      "Supervisor": "Arvind",
      "EnterpriseId-Supervisor": "arvind.walikar",
      "MyTE Approver": "Arvind",
      "EnterpriseId-myteapprover": "arvind.walikar",
      "Userid": "samabati",
      "Contact No": "91 81520-50979",
      "Career Level": "C-SSE",
      "Cisco Manager": "Sylesh",
      "Portfolio name": "ES-Stock",
      "Primary Application": "Stock",
      "Location": "Bangalore",
      "SOW#": "CSCOTQ00092406"
    },
    {
      "Enterprise ID": "ramya.kalaparthi",
      "FirstName": "Ramya",
      "LastName": "Kalaparthi",
      "Supervisor": "Gopi Sammeta",
      "EnterpriseId-Supervisor": "gopi.s.sammeta",
      "MyTE Approver": "Gopi Sammeta",
      "EnterpriseId-myteapprover": "gopi.s.sammeta",
      "Userid": "",
      "Contact No": "",
      "Career Level": "09-Team Lead",
      "Cisco Manager": "F",
      "Portfolio name": "Feb-16",
      "Primary Application": "Feb-16",
      "Location": "Goutam Reddy",
      "SOW#": "GL Lead"
    },
    {
      "Enterprise ID": "sangeeta.naikar",
      "FirstName": "Sangeeta",
      "LastName": "Naikar",
      "Supervisor": "Atul Gupt",
      "EnterpriseId-Supervisor": "atul.gupt",
      "MyTE Approver": "Atul Gupt",
      "EnterpriseId-myteapprover": "atul.gupt",
      "Userid": "snaikar",
      "Contact No": "91 95381-45489",
      "Career Level": "10-Senior Software Engineer",
      "Cisco Manager": "F",
      "Portfolio name": "Feb-15",
      "Primary Application": "Mar-15",
      "Location": "Amy Papciak",
      "SOW#": "WPR-SSBR"
    },
    {
      "Enterprise ID": "subbarao.maniam",
      "FirstName": "Subbarao",
      "LastName": "Maniam",
      "Supervisor": "Phani Bhushan",
      "EnterpriseId-Supervisor": "phani.bhushan.hari",
      "MyTE Approver": "Phani Bhushan",
      "EnterpriseId-myteapprover": "phani.bhushan.hari",
      "Userid": "smaniam",
      "Contact No": "91 99481-92444",
      "Career Level": "10-Senior Software Engineer",
      "Cisco Manager": "M",
      "Portfolio name": "Feb-15",
      "Primary Application": "Mar-15",
      "Location": "Amy Papciak",
      "SOW#": "WPR-SSBR"
    },
    {
      "Enterprise ID": "srikar.pudi",
      "FirstName": "Srikar",
      "LastName": "Pudi",
      "Supervisor": "Sheik Abdullah",
      "EnterpriseId-Supervisor": "sheik.abdullah.m",
      "MyTE Approver": "Sheik Abdullah",
      "EnterpriseId-myteapprover": "sheik.abdullah.m",
      "Userid": "spudi",
      "Contact No": "91 9972179256",
      "Career Level": "10-Senior Software Engineer",
      "Cisco Manager": "M",
      "Portfolio name": "Oct-15",
      "Primary Application": "Oct-15",
      "Location": "Chintan Desai",
      "SOW#": "Finance"
    },
    {
      "Enterprise ID": "govind.rajayogam",
      "FirstName": "Govind",
      "LastName": "Rajay",
      "Supervisor": "Gopi Sammeta",
      "EnterpriseId-Supervisor": "gopi.s.sammeta",
      "MyTE Approver": "Gopi Sammeta",
      "EnterpriseId-myteapprover": "gopi.s.sammeta",
      "Userid": "rgovind",
      "Contact No": "1 4085270817",
      "Career Level": "C-Team Lead",
      "Cisco Manager": "M",
      "Portfolio name": "#N/A",
      "Primary Application": "#N/A",
      "Location": "Romina Parikh",
      "SOW#": "Workforce Analytics & Reporting"
    },
    {
      "Enterprise ID": "r.kumar.agrahari",
      "FirstName": "Ritesh Kumar Agrahari",
      "LastName": "Ritesh Kumar",
      "Supervisor": "Agrahari",
      "EnterpriseId-Supervisor": "Phani Bhushan",
      "MyTE Approver": "phani.bhushan.hari",
      "EnterpriseId-myteapprover": "Phani Bhushan",
      "Userid": "phani.bhushan.hari",
      "Contact No": "Phani Bhushan",
      "Career Level": "phani.bhushan.hari",
      "Cisco Manager": "Phani Bhushan",
      "Portfolio name": "phani.bhushan.hari",
      "Primary Application": "rkumarag",
      "Location": "91 97412-94343",
      "SOW#": "11-Software Engineer"
    },
    {
      "Enterprise ID": "bhaskar.vangimalla",
      "FirstName": "Bhaskar Vangimalla",
      "LastName": "Bhaskar",
      "Supervisor": "Vangimalla",
      "EnterpriseId-Supervisor": "Lokesh Thadani",
      "MyTE Approver": "lokesh.thadani",
      "EnterpriseId-myteapprover": "Lokesh Thadani",
      "Userid": "lokesh.thadani",
      "Contact No": "Lokesh Thadani",
      "Career Level": "lokesh.thadani",
      "Cisco Manager": "Phani Bhushan",
      "Portfolio name": "phani.bhushan.hari",
      "Primary Application": "bvangima",
      "Location": "91 8097864784",
      "SOW#": "10-Senior Software Engineer"
    },
    {
      "Enterprise ID": "veda.penugonda",
      "FirstName": "Veda Lakshmi Penugonda",
      "LastName": "VedaLakshmi",
      "Supervisor": "Penugonda",
      "EnterpriseId-Supervisor": "Abdul Quddus",
      "MyTE Approver": "a.quddus",
      "EnterpriseId-myteapprover": "Abdul Quddus",
      "Userid": "a.quddus",
      "Contact No": "Abdul Quddus",
      "Career Level": "a.quddus",
      "Cisco Manager": "Phani Bhushan",
      "Portfolio name": "phani.bhushan.hari",
      "Primary Application": "",
      "Location": "",
      "SOW#": "11-Software Engineer"
    },
    {
      "Enterprise ID": "jayanti.kumari",
      "FirstName": "Jayanti Kumari",
      "LastName": "Jayanti",
      "Supervisor": "Kumari",
      "EnterpriseId-Supervisor": "Manjunath Bariki",
      "MyTE Approver": "manjunath.bariki",
      "EnterpriseId-myteapprover": "Manjunath Bariki",
      "Userid": "manjunath.bariki",
      "Contact No": "Manjunath Bariki",
      "Career Level": "manjunath.bariki",
      "Cisco Manager": "Niju Thomas",
      "Portfolio name": "niju.thomas",
      "Primary Application": "jakumari",
      "Location": "91 81050-99877",
      "SOW#": "10-Senior Software Engineer"
    },
    {
      "Enterprise ID": "chinu.subudhi",
      "FirstName": "Chinu Subudhi",
      "LastName": "Chinu",
      "Supervisor": "Subudhi",
      "EnterpriseId-Supervisor": "Raghavender",
      "MyTE Approver": "raghavender.jogaraju",
      "EnterpriseId-myteapprover": "Raghavender",
      "Userid": "raghavender.jogaraju",
      "Contact No": "Raghavender",
      "Career Level": "raghavender.jogaraju",
      "Cisco Manager": "Raghavender",
      "Portfolio name": "raghavender.jogaraju",
      "Primary Application": "chisubud",
      "Location": "91 99018-82194",
      "SOW#": "09-Team Lead"
    },
    {
      "Enterprise ID": "jayaprakash.rokkada",
      "FirstName": "Jayaprakash Veerabasappa Rokkada",
      "LastName": "Jayaprakash Veerabasappa",
      "Supervisor": "Rokkada",
      "EnterpriseId-Supervisor": "Niju Thomas",
      "MyTE Approver": "niju.thomas",
      "EnterpriseId-myteapprover": "Niju Thomas",
      "Userid": "niju.thomas",
      "Contact No": "Niju Thomas",
      "Career Level": "niju.thomas",
      "Cisco Manager": "Niju Thomas",
      "Portfolio name": "niju.thomas",
      "Primary Application": "jrokkada",
      "Location": "91  9740516256",
      "SOW#": "08-Associate Manager"
    },
    {
      "Enterprise ID": "atul.gupt",
      "FirstName": "Atul Gupta",
      "LastName": "Atul",
      "Supervisor": "Gupt",
      "EnterpriseId-Supervisor": "Rakesh Thomas",
      "MyTE Approver": "rakesh.thomas",
      "EnterpriseId-myteapprover": "Phani Bhushan",
      "Userid": "phani.bhushan.hari",
      "Contact No": "Phani Bhushan",
      "Career Level": "phani.bhushan.hari",
      "Cisco Manager": "Phani Bhushan",
      "Portfolio name": "phani.bhushan.hari",
      "Primary Application": "atulg2",
      "Location": "91 98869-88859",
      "SOW#": "09-Team Lead"
    },
    {
      "Enterprise ID": "gurpreet.e.kaur",
      "FirstName": "Gurpreet Kaur",
      "LastName": "Gurpreet",
      "Supervisor": "Kaur",
      "EnterpriseId-Supervisor": "Raghavender",
      "MyTE Approver": "raghavender.jogaraju",
      "EnterpriseId-myteapprover": "Raghavender",
      "Userid": "raghavender.jogaraju",
      "Contact No": "Raghavender",
      "Career Level": "raghavender.jogaraju",
      "Cisco Manager": "Raghavender",
      "Portfolio name": "raghavender.jogaraju",
      "Primary Application": "gurpkau2",
      "Location": "91 98455-33536",
      "SOW#": "09-Team Lead"
    },
    {
      "Enterprise ID": "jyoti.a.tiwari",
      "FirstName": "Jyoti Tiwari",
      "LastName": "Jyoti",
      "Supervisor": "Tiwari",
      "EnterpriseId-Supervisor": "Manjunath Bariki",
      "MyTE Approver": "manjunath.bariki",
      "EnterpriseId-myteapprover": "Manjunath Bariki",
      "Userid": "manjunath.bariki",
      "Contact No": "Manjunath Bariki",
      "Career Level": "manjunath.bariki",
      "Cisco Manager": "Niju Thomas",
      "Portfolio name": "niju.thomas",
      "Primary Application": "jtiwari",
      "Location": "91 8088401883",
      "SOW#": "11-Software Engineer"
    },
    {
      "Enterprise ID": "t.selvan",
      "FirstName": "Tamil Selvan Subbaiah",
      "LastName": "Tamil Selvan",
      "Supervisor": "Subbaiah",
      "EnterpriseId-Supervisor": "Niju Thomas",
      "MyTE Approver": "niju.thomas",
      "EnterpriseId-myteapprover": "Niju Thomas",
      "Userid": "niju.thomas",
      "Contact No": "Niju Thomas",
      "Career Level": "niju.thomas",
      "Cisco Manager": "Niju Thomas",
      "Portfolio name": "niju.thomas",
      "Primary Application": "tsubbaia",
      "Location": "91 98 8664 7842",
      "SOW#": "08-Associate Manager"
    },
    {
      "Enterprise ID": "d.novelo.carrillo",
      "FirstName": "David Carrilo",
      "LastName": "David",
      "Supervisor": "Carrillo",
      "EnterpriseId-Supervisor": "Gopi Sammeta",
      "MyTE Approver": "gopi.s.sammeta",
      "EnterpriseId-myteapprover": "Gopi Sammeta",
      "Userid": "gopi.s.sammeta",
      "Contact No": "",
      "Career Level": "",
      "Cisco Manager": "",
      "Portfolio name": "",
      "Primary Application": "",
      "Location": "",
      "SOW#": "10-Senior Software Engineer"
    },
    {
      "Enterprise ID": "satish.sirigirisetty",
      "FirstName": "Satish Sirigirisetty",
      "LastName": "Satish",
      "Supervisor": "Sirigirisetty",
      "EnterpriseId-Supervisor": "Pramod Gupta",
      "MyTE Approver": "pramod.x.gupta",
      "EnterpriseId-myteapprover": "Gopi Sammeta",
      "Userid": "gopi.s.sammeta",
      "Contact No": "",
      "Career Level": "",
      "Cisco Manager": "",
      "Portfolio name": "",
      "Primary Application": "sasirigi",
      "Location": "1 4085270817",
      "SOW#": "C-Team Lead"
    },
    {
      "Enterprise ID": "s.gumma",
      "FirstName": "Srikrishna Gumma",
      "LastName": "Srikrishna",
      "Supervisor": "Gumma",
      "EnterpriseId-Supervisor": "Kiran  Avaral",
      "MyTE Approver": "kiran.avaral",
      "EnterpriseId-myteapprover": "Kiran  Avaral",
      "Userid": "kiran.avaral",
      "Contact No": "",
      "Career Level": "",
      "Cisco Manager": "",
      "Portfolio name": "",
      "Primary Application": "sgumma",
      "Location": "1 4088136697",
      "SOW#": "08-Associate Manager"
    },
    {
      "Enterprise ID": "rakesh.thomas",
      "FirstName": "Rakesh Thomas",
      "LastName": "Rakesh Thomas",
      "Supervisor": "Kizhakkekara",
      "EnterpriseId-Supervisor": "Kiran  Avaral",
      "MyTE Approver": "kiran.avaral",
      "EnterpriseId-myteapprover": "Kiran  Avaral",
      "Userid": "kiran.avaral",
      "Contact No": "",
      "Career Level": "",
      "Cisco Manager": "",
      "Portfolio name": "",
      "Primary Application": "rkizhakk",
      "Location": "1 6124029954",
      "SOW#": "08-Associate Manager"
    },
    {
      "Enterprise ID": "mayank.d.srivastava",
      "FirstName": "Mayank Srivastava",
      "LastName": "Mayank",
      "Supervisor": "Srivastava",
      "EnterpriseId-Supervisor": "Manjunath Bariki",
      "MyTE Approver": "manjunath.bariki",
      "EnterpriseId-myteapprover": "Manjunath Bariki",
      "Userid": "manjunath.bariki",
      "Contact No": "Manjunath Bariki",
      "Career Level": "manjunath.bariki",
      "Cisco Manager": "Niju Thomas",
      "Portfolio name": "niju.thomas",
      "Primary Application": "mayansri",
      "Location": "91 9790767939",
      "SOW#": "10-Senior Software Engineer"
    },
    {
      "Enterprise ID": "a.a.dixit",
      "FirstName": "Abhishek Dixit",
      "LastName": "Abhishek",
      "Supervisor": "Dixit",
      "EnterpriseId-Supervisor": "Abdul Quddus",
      "MyTE Approver": "a.quddus",
      "EnterpriseId-myteapprover": "Abdul Quddus",
      "Userid": "a.quddus",
      "Contact No": "Abdul Quddus",
      "Career Level": "a.quddus",
      "Cisco Manager": "Harish Br",
      "Portfolio name": "harish.br",
      "Primary Application": "abdixit",
      "Location": "91 9739776533",
      "SOW#": "11-Software Engineer"
    },
    {
      "Enterprise ID": "sudeep.goyal",
      "FirstName": "Sudeep Goyal",
      "LastName": "Sudeep",
      "Supervisor": "Goyal",
      "EnterpriseId-Supervisor": "Niju Thomas",
      "MyTE Approver": "niju.thomas",
      "EnterpriseId-myteapprover": "Niju Thomas",
      "Userid": "niju.thomas",
      "Contact No": "Niju Thomas",
      "Career Level": "niju.thomas",
      "Cisco Manager": "Niju Thomas",
      "Portfolio name": "niju.thomas",
      "Primary Application": "sugoyal",
      "Location": "",
      "SOW#": "08-Associate Manager"
    },
    {
      "Enterprise ID": "suneeth.chadalawada",
      "FirstName": "Suneeth Chadalawada",
      "LastName": "Suneeth",
      "Supervisor": "Chadalawada",
      "EnterpriseId-Supervisor": "Gopi Sammeta",
      "MyTE Approver": "gopi.s.sammeta",
      "EnterpriseId-myteapprover": "Gopi Sammeta",
      "Userid": "gopi.s.sammeta",
      "Contact No": "",
      "Career Level": "",
      "Cisco Manager": "",
      "Portfolio name": "",
      "Primary Application": "suchadal",
      "Location": "1 2016006147",
      "SOW#": "C-Associate Manager"
    },
    {
      "Enterprise ID": "praful.kumar.nath",
      "FirstName": "Praful Kumar Nath",
      "LastName": "Praful",
      "Supervisor": "Kumarnath",
      "EnterpriseId-Supervisor": "Lokesh Thadani",
      "MyTE Approver": "lokesh.thadani",
      "EnterpriseId-myteapprover": "Lokesh Thadani",
      "Userid": "lokesh.thadani",
      "Contact No": "Lokesh Thadani",
      "Career Level": "lokesh.thadani",
      "Cisco Manager": "Harish Br",
      "Portfolio name": "harish.br",
      "Primary Application": "",
      "Location": "",
      "SOW#": "C-SSE"
    },
    {
      "Enterprise ID": "prathap.kumar.gowda",
      "FirstName": "Pratap Krishna Singh",
      "LastName": "Pratap Krishna",
      "Supervisor": "Singh",
      "EnterpriseId-Supervisor": "",
      "MyTE Approver": "",
      "EnterpriseId-myteapprover": "",
      "Userid": "",
      "Contact No": "Girisha.adaveeshiah",
      "Career Level": "Girisha.adaveeshiah",
      "Cisco Manager": "Girisha.adaveeshiah",
      "Portfolio name": "Girisha.adaveeshiah",
      "Primary Application": "",
      "Location": "",
      "SOW#": "10-Senior Software Engineer"
    },
    {
      "Enterprise ID": "pallabi.panigrahi",
      "FirstName": "Pallabi Panigrahi",
      "LastName": "Pallabi Panigrahi",
      "Supervisor": "Singh",
      "EnterpriseId-Supervisor": "Atul Gupt",
      "MyTE Approver": "atul.gupt",
      "EnterpriseId-myteapprover": "Atul Gupt",
      "Userid": "atul.gupt",
      "Contact No": "Atul Gupt",
      "Career Level": "atul.gupt",
      "Cisco Manager": "Phani Bhushan",
      "Portfolio name": "phani.bhushan.hari",
      "Primary Application": "ppanigra",
      "Location": "91 98866-60524",
      "SOW#": "11-Software Engineer"
    },
    {
      "Enterprise ID": "chetan.b.gupta",
      "FirstName": "Chetan Gupta",
      "LastName": "Chetan",
      "Supervisor": "Gupta",
      "EnterpriseId-Supervisor": "Phani Bhushan",
      "MyTE Approver": "phani.bhushan.hari",
      "EnterpriseId-myteapprover": "Phani Bhushan",
      "Userid": "phani.bhushan.hari",
      "Contact No": "Phani Bhushan",
      "Career Level": "phani.bhushan.hari",
      "Cisco Manager": "Phani Bhushan",
      "Portfolio name": "phani.bhushan.hari",
      "Primary Application": "",
      "Location": "",
      "SOW#": "11-Software Engineer"
    },
    {
      "Enterprise ID": "abhis.gupta",
      "FirstName": "Abhishek Gupta",
      "LastName": "Abhishek",
      "Supervisor": "Gupta",
      "EnterpriseId-Supervisor": "Tirumala",
      "MyTE Approver": "tirumala.betamcharla",
      "EnterpriseId-myteapprover": "Tirumala",
      "Userid": "tirumala.betamcharla",
      "Contact No": "Tirumala",
      "Career Level": "tirumala.betamcharla",
      "Cisco Manager": "Raghavender",
      "Portfolio name": "raghavender.jogaraju",
      "Primary Application": "abgupta4",
      "Location": "91 98966-59894",
      "SOW#": "10-Senior Software Engineer"
    },
    {
      "Enterprise ID": "m.kempaiah",
      "FirstName": "#REF!",
      "LastName": "Mahadevaswamy",
      "Supervisor": "Kempaiah",
      "EnterpriseId-Supervisor": "Annada Prasanna",
      "MyTE Approver": "a.prasanna.sahoo",
      "EnterpriseId-myteapprover": "Annada Prasanna",
      "Userid": "a.prasanna.sahoo",
      "Contact No": "Annada Prasanna",
      "Career Level": "a.prasanna.sahoo",
      "Cisco Manager": "Raghavender",
      "Portfolio name": "raghavender.jogaraju",
      "Primary Application": "mahkempa",
      "Location": "91 90089-48014",
      "SOW#": "10-Senior Software Engineer"
    },
    {
      "Enterprise ID": "anuradha.basavaraju",
      "FirstName": "Anuradha Basavaraju",
      "LastName": "Anuradha",
      "Supervisor": "Basavaraju",
      "EnterpriseId-Supervisor": "Harish Br",
      "MyTE Approver": "harish.br",
      "EnterpriseId-myteapprover": "Harish Br",
      "Userid": "harish.br",
      "Contact No": "Harish Br",
      "Career Level": "harish.br",
      "Cisco Manager": "Harish Br",
      "Portfolio name": "harish.br",
      "Primary Application": "anub",
      "Location": "91 9986215431",
      "SOW#": "09-Team Lead"
    },
    {
      "Enterprise ID": "v.venkatarathnam",
      "FirstName": "Vinitha Venkatarathnam",
      "LastName": "Vinitha",
      "Supervisor": "Venkatarathnam",
      "EnterpriseId-Supervisor": "Phani Bhushan",
      "MyTE Approver": "phani.bhushan.hari",
      "EnterpriseId-myteapprover": "Phani Bhushan",
      "Userid": "phani.bhushan.hari",
      "Contact No": "Phani Bhushan",
      "Career Level": "phani.bhushan.hari",
      "Cisco Manager": "Phani Bhushan",
      "Portfolio name": "phani.bhushan.hari",
      "Primary Application": "",
      "Location": "",
      "SOW#": "12-Associate Software Engineer"
    },
    {
      "Enterprise ID": "n.nayak",
      "FirstName": "Neha Nayak",
      "LastName": "Neha",
      "Supervisor": "Nayak",
      "EnterpriseId-Supervisor": "Phani Bhushan",
      "MyTE Approver": "phani.bhushan.hari",
      "EnterpriseId-myteapprover": "Phani Bhushan",
      "Userid": "phani.bhushan.hari",
      "Contact No": "Phani Bhushan",
      "Career Level": "phani.bhushan.hari",
      "Cisco Manager": "Phani Bhushan",
      "Portfolio name": "phani.bhushan.hari",
      "Primary Application": "",
      "Location": "",
      "SOW#": "12-Associate Software Engineer"
    },
    {
      "Enterprise ID": "",
      "FirstName": "siva.nekkalapudi",
      "LastName": "Siva Nekkalapudi",
      "Supervisor": "Siva",
      "EnterpriseId-Supervisor": "Nekkalapudi",
      "MyTE Approver": "Srinivasa Sunchu",
      "EnterpriseId-myteapprover": "srinivasa.sunchu",
      "Userid": "Srinivasa Sunchu",
      "Contact No": "srinivasa.sunchu",
      "Career Level": "",
      "Cisco Manager": "",
      "Portfolio name": "",
      "Primary Application": "",
      "Location": "snekkala",
      "SOW#": 8326556789,
      "": "No"
    },
    {
      "Enterprise ID": "ashok.renukaradhya",
      "FirstName": "Ashok Panditanahalli",
      "LastName": "Renukaradhya",
      "Supervisor": "Tirumala",
      "EnterpriseId-Supervisor": "tirumala.betamcharla",
      "MyTE Approver": "Tirumala",
      "EnterpriseId-myteapprover": "tirumala.betamcharla",
      "Userid": "arenukar",
      "Contact No": "91 9731887942",
      "Career Level": "10-Senior Software Engineer",
      "Cisco Manager": "Sangeetha R",
      "Portfolio name": "P2R-My Expense",
      "Primary Application": "My Expense",
      "Location": "Bangalore",
      "SOW#": "CSCOTQ00091810"
    },
    {
      "Enterprise ID": "anvesh.singamsetty",
      "FirstName": "Anvesh Singamsetty",
      "LastName": "Anvesh",
      "Supervisor": "Singamsetty",
      "EnterpriseId-Supervisor": "phani.bhushan.hari",
      "MyTE Approver": "Phani Bhushan",
      "EnterpriseId-myteapprover": "phani.bhushan.hari",
      "Userid": "asingams",
      "Contact No": "+91 81231-46869",
      "Career Level": "11-Software Engineer",
      "Cisco Manager": "Amy Papciak",
      "Portfolio name": "WPR-SSBR",
      "Primary Application": "WPR Allocations",
      "Location": "Bangalore",
      "SOW#": "CSCOTQ00092136"
    }
  ]
}
